[
  {
    "name": "Justice David",
    "email": "davidaboy671@gmail.com",
    "refs": [
      "manual_fix_20260402_Mk7DUqzYtlhQx0shw9Mq2koybc12"
    ],
    "activationRows": [],
    "reason": "not_present"
  },
  {
    "name": "KILANKO FOLASAYO",
    "email": "kilankofola020@gmail.com",
    "refs": [
      "TX_1775498873816_97854",
      "TX_1775498586427_84447",
      "TX_1775498827166_99127",
      "TX_1775498827168_46953"
    ],
    "activationRows": [],
    "reason": "not_present"
  },
  {
    "name": "Mabel Nebo",
    "email": "mabelnebo80@gmail.com",
    "refs": [
      "TX_1775498537128_54697",
      "TX_1775498378511_99029",
      "TX_1775498378509_91495"
    ],
    "activationRows": [],
    "reason": "not_present"
  },
  {
    "name": "Elisha Linus",
    "email": "elishalinus1@gmail.com",
    "refs": [
      "TX_1775497751473_14391",
      "TX_1775497618067_75521"
    ],
    "activationRows": [],
    "reason": "not_present"
  },
  {
    "name": "Kayopa Woyengimiebifagha",
    "email": "miebikayopa@gmail.com",
    "refs": [
      "TX_1775552597225_2033",
      "TX_1775552239205_35811",
      "MNFY|55|20260407095722|276628"
    ],
    "activationRows": [],
    "reason": "not_present"
  },
  {
    "name": "Blessing Izikire",
    "email": "blessingizikire360@gmail.com",
    "refs": [
      "TX_1775561455283_73909",
      "TX_1775560317709_38017",
      "TX_1775560317709_32866",
      "TX_1775560317707_33597",
      "MNFY|75|20260407121204|283297"
    ],
    "activationRows": [],
    "reason": "not_present"
  },
  {
    "name": "Dalhatu Haruna Muhammad",
    "email": "zazoodiamond@gmail.com",
    "refs": [
      "TX_1775562532053_4876",
      "TX_1775561018334_59616",
      "TX_1775562444456_68520"
    ],
    "activationRows": [],
    "reason": "not_present"
  },
  {
    "name": "Efe richard",
    "email": "richardeferi@gmail.com",
    "refs": [
      "TX_1775573256367_69783",
      "TX_1775571470874_6145",
      "TX_1775571470876_57724",
      "MNFY|93|20260407151756|042485"
    ],
    "activationRows": [],
    "reason": "not_present"
  },
  {
    "name": "Nwafor Onyinyechi Maryann",
    "email": "onyinyechimaryannnwafor@gmail.com",
    "refs": [
      "TX_1775587341339_44507",
      "TX_1775578230349_53449",
      "TX_1775578409343_90115",
      "TX_1775585317028_5402",
      "TX_1775585404756_23022",
      "TX_1775587046137_25454",
      "TX_1775587046138_3070",
      "TX_1775587122144_58406",
      "TX_1775587122142_12612"
    ],
    "activationRows": [],
    "reason": "not_present"
  },
  {
    "name": "ALAMU FOLAWE DANIEL",
    "email": "alamufolawe@gmail.com",
    "refs": [
      "TX_1775587248761_53994",
      "TX_1775586611702_87848",
      "TX_1775587033459_82440"
    ],
    "activationRows": [],
    "reason": "not_present"
  },
  {
    "name": "Olawale Bello",
    "email": "olawalbell52@gmail.com",
    "refs": [
      "TX_1775586960099_75062",
      "TX_1775586700356_21879",
      "TX_1775586700355_63252",
      "TX_1775586960098_54388"
    ],
    "activationRows": [],
    "reason": "not_present"
  },
  {
    "name": "Fvry",
    "email": "ayomikun370@gmail.com",
    "refs": [
      "TX_1775584233980_77090",
      "TX_1775584184397_22579"
    ],
    "activationRows": [],
    "reason": "not_present"
  },
  {
    "name": "Salihu",
    "email": "muhammadsalisumahammad@gmail.com",
    "refs": [
      "TX_1775583594031_72433",
      "TX_1775583594030_89599"
    ],
    "activationRows": [],
    "reason": "not_present"
  },
  {
    "name": "Wasiu Sodiq Ajibola",
    "email": "wasiuayinde1950@gmail.com",
    "refs": [
      "TX_1775581223854_39423"
    ],
    "activationRows": [],
    "reason": "not_present"
  },
  {
    "name": "zakaria Muzamil",
    "email": "zakariamuzamil39@gmail.com",
    "refs": [
      "TX_1775580690906_84848"
    ],
    "activationRows": [],
    "reason": "not_present"
  },
  {
    "name": "Abdulsemiu Solihat",
    "email": "Abdulsemiusolihat@icloud.com",
    "refs": [
      "TX_1775575484683_96782"
    ],
    "activationRows": [],
    "reason": "not_present"
  },
  {
    "name": "Joy Ikem",
    "email": "joypaulinus93@gmail.com",
    "refs": [
      "unknown"
    ],
    "activationRows": [],
    "reason": "not_present"
  },
  {
    "name": "Micheal okechukwu okereke",
    "email": "okechukwum46@gmail.com",
    "refs": [
      "TX_1775522632059_32044"
    ],
    "activationRows": [],
    "reason": "not_present"
  },
  {
    "name": "Ine Jonathan Jack",
    "email": "inejonathanjack@gmail.com",
    "refs": [
      "TX_1775641786601_54418",
      "TX_1775637927780_72411",
      "TX_1775638766576_53393"
    ],
    "activationRows": [],
    "reason": "not_present"
  },
  {
    "name": "Sarah Olawuyi",
    "email": "susa12993@gmail.com",
    "refs": [
      "TX_1775629055423_29908",
      "TX_1775628871341_31290"
    ],
    "activationRows": [],
    "reason": "not_present"
  },
  {
    "name": "Edet Jumbo okon",
    "email": "edeto3671@gmail.com",
    "refs": [
      "TX_1775645399406_76788",
      "TX_1775645290331_7408",
      "TX_1775936928752_32639"
    ],
    "activationRows": [],
    "reason": "not_present"
  },
  {
    "name": "Ozoekwem Chiadika Anthony",
    "email": "ozoekwemchiadika@gmail.com",
    "refs": [
      "TX_1775605024153_59331",
      "TX_1775603351248_15571",
      "TX_1775603516297_71820",
      "TX_1775603516298_19887",
      "TX_1775603749068_89102",
      "TX_1775603826139_48040"
    ],
    "activationRows": [],
    "reason": "not_present"
  },
  {
    "name": "Goodness Taiwo",
    "email": "r55uwheine@gmail.com",
    "refs": [
      "TX_1775675342746_54892",
      "TX_1775675126284_2515",
      "TX_1775675172147_29196",
      "TX_1775675172145_97248"
    ],
    "activationRows": [],
    "reason": "not_present"
  },
  {
    "name": "PATIENCE CHIKODI NWOKENKWO",
    "email": "patiencenwokenkwo@gmail.com",
    "refs": [
      "TX_1775717137613_9350",
      "TX_1775716154073_72703",
      "TX_1775716312610_38917",
      "TX_1775716668952_75952"
    ],
    "activationRows": [],
    "reason": "not_present"
  },
  {
    "name": "Johnisaac",
    "email": "isaacjohnassogba3@gmail.com",
    "refs": [
      "TX_1775494347284_41222"
    ],
    "activationRows": [],
    "reason": "not_present"
  },
  {
    "name": "oluwagbemiga ransom",
    "email": "oluwagbemigaransom14@gmail.com",
    "refs": [
      "TX_1775732147957_19170",
      "TX_1775731965652_3756",
      "TX_1775731965652_94170",
      "TX_1775731965652_10666",
      "TX_1775732068510_42549",
      "TX_1775732068511_10274",
      "TX_1775495640971_65732"
    ],
    "activationRows": [],
    "reason": "not_present"
  },
  {
    "name": "Abubakar Adamu",
    "email": "youngkalee0@gmail.com",
    "refs": [
      "TX_1775744838335_3638",
      "TX_1775744094567_71622",
      "TX_1775744120461_10856",
      "TX_1775744310746_77102",
      "TX_1775744496556_10650"
    ],
    "activationRows": [],
    "reason": "not_present"
  },
  {
    "name": "Salami Comfort Titilope",
    "email": "hassanomotayo14@gmail.com",
    "refs": [
      "TX_1775808904410_72431",
      "TX_1775808741814_61644"
    ],
    "activationRows": [],
    "reason": "not_present"
  },
  {
    "name": "Sobayo Samuel Abiodun",
    "email": "samuelsobayo67@gmail.com",
    "refs": [
      "TX_1775826421677_14559",
      "TX_1775826196110_66688"
    ],
    "activationRows": [],
    "reason": "not_present"
  },
  {
    "name": "Jabir Yusuf",
    "email": "jabiryusuf098@gmail.com",
    "refs": [
      "TX_1775842135986_41134",
      "TX_1775840510633_63142",
      "TX_1775840549769_34783",
      "TX_1775840572392_75041",
      "TX_1775841604761_50856",
      "TX_1775841659850_87347"
    ],
    "activationRows": [],
    "reason": "not_present"
  },
  {
    "name": "Endurance Otemeh",
    "email": "otemehendurance@gmail.com",
    "refs": [
      "TX_1775851934977_66389",
      "TX_1775850883093_5451",
      "TX_1775850883102_22831",
      "TX_1775850883102_53195",
      "TX_1775850883102_41042",
      "TX_1775850883102_74627",
      "TX_1775850883102_33463",
      "TX_1775850883102_67703",
      "TX_1775851525964_26827",
      "TX_1775851525965_85861",
      "TX_1775851525965_7065",
      "TX_1775851525965_20433",
      "TX_1775851525965_58752"
    ],
    "activationRows": [],
    "reason": "not_present"
  },
  {
    "name": "Prosper Prince",
    "email": "coleethan636@gmail.com",
    "refs": [
      "TX_1775859340932_69905",
      "TX_1775858504629_79098",
      "TX_1775858504628_9232",
      "TX_1775859340931_5682"
    ],
    "activationRows": [],
    "reason": "not_present"
  },
  {
    "name": "Peter Elizabeth Omomate",
    "email": "elizabethpeter079@gmail.com",
    "refs": [
      "MNFY|69|20260411080725|027292",
      "MNFY|93|20260411162434|039472",
      "TX_1775921070335_80773"
    ],
    "activationRows": [],
    "reason": "not_present"
  },
  {
    "name": "Chidinma Iheanacho Favour",
    "email": "chidinmafavour784@gmail.com",
    "refs": [
      "TX_1775925966535_22337",
      "TX_1775925674451_26459",
      "TX_1775925674448_87185"
    ],
    "activationRows": [],
    "reason": "not_present"
  },
  {
    "name": "Mobolaji Olabisi",
    "email": "bjalash@gmail.com",
    "refs": [
      "TX_1775972916272_93567",
      "TX_1775953068980_31260"
    ],
    "activationRows": [],
    "reason": "not_present"
  },
  {
    "name": "JAHSWILL UCHECHUKE ABRAHAM",
    "email": "abrahamjahswill020@gmail.com",
    "refs": [
      "TX_1775952305726_79645",
      "TX_1775952108655_89962"
    ],
    "activationRows": [],
    "reason": "not_present"
  },
  {
    "name": "Chibueze Chibyke",
    "email": "joachimchibueze748@gmail.com",
    "refs": [
      "TX_1775951481547_8165",
      "TX_1775951316712_25435",
      "TX_1775951316710_88675",
      "TX_1775951481544_67040"
    ],
    "activationRows": [],
    "reason": "not_present"
  },
  {
    "name": "Azeez Rukayah",
    "email": "Abdulazeezrukky55@gmail.com",
    "refs": [
      "TX_1775947515439_19640",
      "TX_1775947123747_82245",
      "TX_1775947316010_54965"
    ],
    "activationRows": [],
    "reason": "not_present"
  },
  {
    "name": "Chigozie nwazuruike",
    "email": "doyouwantohear@gmail.com",
    "refs": [
      "TX_1775946236124_86737",
      "TX_1775946236125_50182"
    ],
    "activationRows": [],
    "reason": "not_present"
  },
  {
    "name": "Shola",
    "email": "sholatogbe@gmail.com",
    "refs": [
      "TX_1775945169534_98334",
      "TX_1775945169533_97870",
      "TX_1775945169534_60455",
      "TX_1775945169534_55474",
      "TX_1776017309468_21049"
    ],
    "activationRows": [],
    "reason": "not_present"
  },
  {
    "name": "Isah Yusuf Adomu",
    "email": "adomu2022@gmail.com",
    "refs": [
      "TX_1775989031893_58040",
      "TX_1775989031891_82212",
      "MNFY|42|20260412111738|066621",
      "TX_1775989055922_48059",
      "MNFY|95|20260412011750|049798",
      "TX_1775953068980_31260"
    ],
    "activationRows": [],
    "reason": "not_present"
  },
  {
    "name": "Peter habila",
    "email": "habilapeter779@gmail.com",
    "refs": [
      "TX_1775988915611_97359",
      "TX_1775989049267_7124",
      "TX_1775989049267_30382",
      "TX_1775989049264_45925"
    ],
    "activationRows": [],
    "reason": "not_present"
  },
  {
    "name": "Olawumi Hanifat Olayinka",
    "email": "olawumihanifat23@gmail.com",
    "refs": [
      "TX_1776004782764_98860",
      "TX_1776004782763_56714"
    ],
    "activationRows": [],
    "reason": "not_present"
  },
  {
    "name": "Vitalis buka",
    "email": "ebukavitalis779@gmail.com",
    "refs": [
      "TX_1776028108681_74104",
      "TX_1776027508271_86326",
      "TX_1776028108681_94649"
    ],
    "activationRows": [],
    "reason": "not_present"
  },
  {
    "name": "Anthony Vera",
    "email": "azzzzma53@gmail.com",
    "refs": [
      "TX_1776029537256_64314",
      "TX_1776029537256_19723",
      "TX_1776039800787_33942"
    ],
    "activationRows": [],
    "reason": "not_present"
  },
  {
    "name": "DAMILOLA OMOTOSO",
    "email": "adewoledamilola87@gmail.com",
    "refs": [
      "TX_1776061033580_71219",
      "TX_1776060168934_77050",
      "TX_1776060466340_51396",
      "TX_1776060495563_61040",
      "TX_1776060549548_59873",
      "TX_1776060568223_95014"
    ],
    "activationRows": [],
    "reason": "not_present"
  },
  {
    "name": "Abiodun Oluwaseyi kolapo",
    "email": "princeabiodun268@gmail.com",
    "refs": [
      "TX_1776071067020_73568",
      "TX_1776071067019_51454"
    ],
    "activationRows": [],
    "reason": "not_present"
  },
  {
    "name": "FIDELIS NATHANIEL",
    "email": "fidelisnathaniel15@gmail.com",
    "refs": [
      "TX_1776082978823_35187"
    ],
    "activationRows": [],
    "reason": "not_present"
  },
  {
    "name": "Owojuyigbe Folakemi",
    "email": "folaowojuyigbe@gmail.com",
    "refs": [
      "TX_1776084086339_15882"
    ],
    "activationRows": [],
    "reason": "not_present"
  },
  {
    "name": "Honey drop",
    "email": "oladipupooyinkansola866@gmail.com",
    "refs": [
      "TX_1776085690367_50965"
    ],
    "activationRows": [],
    "reason": "not_present"
  },
  {
    "name": "Abdulwasiu Ramat omolewa",
    "email": "abdulwasiuramatomolewa@gmail.com",
    "refs": [
      "TX_1776106079123_79961"
    ],
    "activationRows": [],
    "reason": "not_present"
  },
  {
    "name": "PRAYER EZEDIALU",
    "email": "prayerezedialu914@gmail.com",
    "refs": [
      "TX_1776108226106_36145",
      "TX_1775983911100_80541"
    ],
    "activationRows": [],
    "reason": "not_present"
  },
  {
    "name": "Joshua kamsi",
    "email": "joshuakamsi009@gmail.com",
    "refs": [
      "TX_1776105927064_82812"
    ],
    "activationRows": [],
    "reason": "not_present"
  },
  {
    "name": "Usman Muhammad",
    "email": "um578447@gmail.com",
    "refs": [
      "TX_1776112434207_81141"
    ],
    "activationRows": [],
    "reason": "not_present"
  },
  {
    "name": "Godgift Obasiya",
    "email": "godgiftobasiya2@gmail.com",
    "refs": [
      "TX_1776144906434_9546"
    ],
    "activationRows": [],
    "reason": "not_present"
  },
  {
    "name": "Okedeji Femi Emmanuel",
    "email": "femiokedeji@gmail.com",
    "refs": [
      "TX_1776151346913_68621",
      "TX_1776064547478_22189"
    ],
    "activationRows": [],
    "reason": "not_present"
  },
  {
    "name": "Muhammad Usman Ahmad",
    "email": "mahmed3196@gmail.com",
    "refs": [
      "TX_1776148719513_28631"
    ],
    "activationRows": [],
    "reason": "not_present"
  },
  {
    "name": "Godday Osasere",
    "email": "goddayosasere@gmail.com",
    "refs": [
      "TX_1776159412442_96285",
      "TX_1776153569583_90761",
      "TX_1776153569582_83807",
      "TX_1776153603402_69275",
      "TX_1776153603401_93433",
      "TX_1776159412441_14598"
    ],
    "activationRows": [],
    "reason": "not_present"
  },
  {
    "name": "Olalekan Oludiran",
    "email": "kvngtushie@gmail.com",
    "refs": [
      "TX_1776149397186_74536"
    ],
    "activationRows": [],
    "reason": "not_present"
  },
  {
    "name": "Eddykesh",
    "email": "edwardfrancis866@gmail.com",
    "refs": [
      "TX_1776162659703_8514",
      "TX_1776162659702_24079"
    ],
    "activationRows": [],
    "reason": "not_present"
  },
  {
    "name": "Shittu Abdulbasit",
    "email": "shittubasit473@gmail.com",
    "refs": [
      "TX_1776180771292_11030",
      "TX_1776176798225_64573",
      "TX_1776176798224_65098",
      "TX_1776176798225_93052",
      "TX_1776176798225_69117",
      "TX_1776176798223_50745",
      "TX_1776180771291_2957",
      "MNFY|42|20260414163257|023027"
    ],
    "activationRows": [],
    "reason": "not_present"
  },
  {
    "name": "Bamidele Franck",
    "email": "franck.bams@gmail.com",
    "refs": [
      "TX_1776185219979_8322",
      "TX_1776184983258_7056"
    ],
    "activationRows": [],
    "reason": "not_present"
  },
  {
    "name": "Bliss Harrison",
    "email": "ukaigwebliss2010@gmail.com",
    "refs": [
      "TX_1776188607063_97183",
      "TX_1776188495710_73102"
    ],
    "activationRows": [],
    "reason": "not_present"
  },
  {
    "name": "Solomon Nworie",
    "email": "nworiesolomon65@gmail.com",
    "refs": [
      "TX_1776232788023_94601",
      "TX_1776232592027_16943",
      "TX_1776232592027_24829"
    ],
    "activationRows": [],
    "reason": "not_present"
  },
  {
    "name": "Pearl Diepreye Reuben",
    "email": "pearlistic2001@gmail.com",
    "refs": [
      "TX_1776707837182_44240",
      "TX_1776707625604_35467",
      "TX_1776707694147_51039"
    ],
    "activationRows": [],
    "reason": "not_present"
  },
  {
    "name": "Emem Jack",
    "email": "jackemem92@gmail.com",
    "refs": [
      "TX_1777883285182_96400",
      "TX_1777882885558_19895",
      "TX_1777883115339_73793"
    ],
    "activationRows": [],
    "reason": "not_present"
  },
  {
    "name": "Hope Ndifreke",
    "email": "hopendifreke41@gmail.com",
    "refs": [
      "TX_1778592508723_27974",
      "TX_1778591966963_69778",
      "TX_1778592018906_64148",
      "TX_1778592266471_74104",
      "TX_1778592410544_46345"
    ],
    "activationRows": [],
    "reason": "not_present"
  },
  {
    "name": "Enuesika Dennis Somadina",
    "email": "truckscompany954@gmail.com",
    "refs": [
      "TX_1778607383717_11763",
      "TX_1776615255380_19255",
      "TX_1778607088877_15470"
    ],
    "activationRows": [],
    "reason": "not_present"
  },
  {
    "name": "Odah benjamin",
    "email": "odahbenjamin4@gmail.com",
    "refs": [
      "TX_1778659957028_52395"
    ],
    "activationRows": [],
    "reason": "not_present"
  },
  {
    "name": "Joseph Enoch",
    "email": "festus119229881@gmail.com",
    "refs": [
      "TX_1778821443265_39137",
      "TX_1778821137924_96026",
      "TX_1778821260557_31831"
    ],
    "activationRows": [],
    "reason": "not_present"
  },
  {
    "name": "Adaeze Divine",
    "email": "divineadaeze92@gmail.com",
    "refs": [
      "TX_1779166476137_82222",
      "TX_1779140004477_35783",
      "TX_1779140064671_27633",
      "TX_1779166128136_32770"
    ],
    "activationRows": [],
    "reason": "not_present"
  },
  {
    "name": "Balogun Korede",
    "email": "balogunkorede2222@gmail.com",
    "refs": [
      "TX_1779179518985_90324",
      "TX_1779179377960_35680"
    ],
    "activationRows": [],
    "reason": "not_present"
  },
  {
    "name": "Ekwulonu Helen Chimezirim",
    "email": "helchimex@yahoo.com",
    "refs": [
      "TX_1779188070895_3041",
      "TX_1779187942377_88496"
    ],
    "activationRows": [],
    "reason": "not_present"
  },
  {
    "name": "Isiaka yomi olaoshebikan",
    "email": "abayomiadewale365@gmail.com",
    "refs": [
      "TX_1779196317461_97623",
      "TX_1779194388481_80849",
      "TX_1779196186316_1851",
      "TX_1779196210886_69610"
    ],
    "activationRows": [],
    "reason": "not_present"
  },
  {
    "name": "Aregu, Agatha Danlami",
    "email": "areguagatha@gmail.com",
    "refs": [
      "TX_1779213012414_84028",
      "TX_1779212653677_26707",
      "TX_1779212829417_40011",
      "TX_1779212878802_19532"
    ],
    "activationRows": [],
    "reason": "not_present"
  },
  {
    "name": "Ganiyu Abdulmalik",
    "email": "abdulmalikayo287@gmail.com",
    "refs": [
      "TX_1779219515099_16921",
      "TX_1779219253150_25185"
    ],
    "activationRows": [],
    "reason": "not_present"
  },
  {
    "name": "Abdulazeez Isah",
    "email": "abdulazizisah04@gmail.com",
    "refs": [
      "TX_1779223940096_88412",
      "TX_1779223634516_85224",
      "TX_1779223696777_59571"
    ],
    "activationRows": [],
    "reason": "not_present"
  },
  {
    "name": "Grace Moronfade",
    "email": "alexbalogun593@gmail.com",
    "refs": [
      "TX_1779227231148_99759",
      "TX_1779227058752_39817"
    ],
    "activationRows": [],
    "reason": "not_present"
  },
  {
    "name": "Victor Nwachukwu",
    "email": "selenacampos017@gmail.com",
    "refs": [
      "TX_1779228416325_3131",
      "TX_1779228272034_5927"
    ],
    "activationRows": [],
    "reason": "not_present"
  },
  {
    "name": "Ogunwumi ojo samuel",
    "email": "ojojames934@gmail.com",
    "refs": [
      "TX_1779274095761_83651",
      "TX_1779273861829_46322",
      "TX_1779274010956_93946"
    ],
    "activationRows": [],
    "reason": "not_present"
  },
  {
    "name": "Godswill Jackson Monday",
    "email": "godswillmonday736@gmail.com",
    "refs": [
      "TX_1779279527948_77357",
      "TX_1779279181777_46939"
    ],
    "activationRows": [],
    "reason": "not_present"
  },
  {
    "name": "chidera",
    "email": "onumonuchidera1@gmail.com",
    "refs": [
      "TX_1779281370860_89555",
      "TX_1779281107397_1802"
    ],
    "activationRows": [],
    "reason": "not_present"
  },
  {
    "name": "Bei kem",
    "email": "munonyedic22@gmail.com",
    "refs": [
      "TX_1779286247957_27198",
      "TX_1779285429005_77607",
      "TX_1779285429004_16887",
      "TX_1779286132347_21648"
    ],
    "activationRows": [],
    "reason": "not_present"
  },
  {
    "name": "Funkekeme Cameroon",
    "email": "funkekemecameroon247@gmail.com",
    "refs": [
      "TX_1779346226698_21734",
      "TX_1779219368269_68433",
      "TX_1779284511124_74288",
      "TX_1779344987712_99039",
      "TX_1779345440222_75462"
    ],
    "activationRows": [],
    "reason": "not_present"
  },
  {
    "name": "Rebecca ishaya peni",
    "email": "beckyishaya31@gmail.com",
    "refs": [
      "TX_1779346215105_56364",
      "TX_1779344784294_37593"
    ],
    "activationRows": [],
    "reason": "not_present"
  },
  {
    "name": "chibuike",
    "email": "chibuike4771@gmail.com",
    "refs": [
      "TX_1779357508782_5819",
      "TX_1779271972776_50418",
      "TX_1779356924949_458",
      "TX_1779357104893_5119"
    ],
    "activationRows": [],
    "reason": "not_present"
  },
  {
    "name": "Adeyeye taiwo bosede",
    "email": "aygold988@gmail.com",
    "refs": [
      "TX_1779394939167_89233",
      "TX_1779394450824_62443",
      "TX_1779394452690_76856",
      "TX_1779394578148_30524",
      "TX_1779394829307_6552"
    ],
    "activationRows": [],
    "reason": "not_present"
  },
  {
    "name": "Precious John aneke",
    "email": "preciousemeka8499@gmail.com",
    "refs": [
      "TX_1779438306959_25540",
      "TX_1779436920835_69044",
      "TX_1779438060997_3870"
    ],
    "activationRows": [],
    "reason": "not_present"
  },
  {
    "name": "Gift Ehi peter",
    "email": "pehi71355@gmail.com",
    "refs": [
      "TX_1779548422291_24810",
      "TX_1779548258578_11593"
    ],
    "activationRows": [],
    "reason": "not_present"
  },
  {
    "name": "Michael Adama",
    "email": "michaeladama482@gmail.com",
    "refs": [
      "TX_1779566131695_22626",
      "TX_1779565938057_59547"
    ],
    "activationRows": [],
    "reason": "not_present"
  },
  {
    "name": "Akiode Daniel",
    "email": "slicerdcff@gmail.com",
    "refs": [
      "TX_1779797982595_81103",
      "TX_1779797288229_63441",
      "TX_1779797418999_96739",
      "TX_1779797499084_76603",
      "TX_1779797523599_39589",
      "TX_1779797643576_5423",
      "TX_1779797708184_98487"
    ],
    "activationRows": [],
    "reason": "not_present"
  },
  {
    "name": "Nweke Ifeoma Ụgbala",
    "email": "ifeyras44@gmail.com",
    "refs": [
      "TX_1779870705686_95220",
      "TX_1779870285946_1213"
    ],
    "activationRows": [],
    "reason": "not_present"
  },
  {
    "name": "David George",
    "email": "davidjosephchigozie@gmail.com",
    "refs": [
      "TX_1779999753864_29324",
      "TX_1779969798354_57936",
      "TX_1779983302699_15248",
      "TX_1779983489375_71456",
      "TX_1779983621489_2639",
      "TX_1779983768878_41395",
      "TX_1779983895784_18989",
      "TX_1779994289665_61006"
    ],
    "activationRows": [],
    "reason": "not_present"
  },
  {
    "name": "Charles M. Oloworaran",
    "email": "",
    "refs": [
      "TX_1780002102205_33361",
      "TX_1780001240632_69112",
      "TX_1780001690407_2113"
    ],
    "activationRows": [],
    "reason": "not_present"
  },
  {
    "name": "Goma Michael",
    "email": "joymargaret500@gmail.com",
    "refs": [
      "TX_1780160525827_41466",
      "TX_1780157898568_30050",
      "TX_1780159640555_76907",
      "TX_1780159722556_38052",
      "TX_1780159777215_67112",
      "TX_1780160082831_1282"
    ],
    "activationRows": [],
    "reason": "not_present"
  },
  {
    "name": "Samuel Edet Etinefio",
    "email": "harrysamuel080@gmail.com",
    "refs": [
      "TX_1780432956262_68559",
      "MNFY|68|20260602214303|004612",
      "TX_1780432978652_80642"
    ],
    "activationRows": [],
    "reason": "not_present"
  },
  {
    "name": "Aisha Ahmed",
    "email": "aishaahma002@gmail.com",
    "refs": [
      "TX_1780442084393_79295",
      "MNFY|91|20260603001841|009024",
      "TX_1780442319696_87091"
    ],
    "activationRows": [],
    "reason": "not_present"
  },
  {
    "name": "Godwin samuel john",
    "email": "godorns6@gmail.com",
    "refs": [
      "TX_1780563837204_19233",
      "MNFY|33|20260604100748|061594",
      "TX_1780564064084_5108"
    ],
    "activationRows": [],
    "reason": "not_present"
  },
  {
    "name": "Kpaama Seth Bariela",
    "email": "elasqueenunarrested@gmail.com",
    "refs": [
      "TX_1780569277812_47053",
      "MNFY|52|20260604113913|064120",
      "TX_1780569549391_93991"
    ],
    "activationRows": [],
    "reason": "not_present"
  },
  {
    "name": "Valentine Raymond",
    "email": "valentine00vbou@gmail.com",
    "refs": [
      "TX_1780338571740_39713",
      "TX_1780338289546_16130",
      "TX_1780338377373_85410",
      "MNFY|44|20260601192451|066059"
    ],
    "activationRows": [],
    "reason": "not_present"
  },
  {
    "name": "John wike",
    "email": "favour254123@gmail.com",
    "refs": [
      "TX_1780563383277_83466",
      "TX_1779872200264_72449",
      "TX_1779872462596_91363",
      "TX_1779872668810_18130",
      "TX_1779873518679_18249",
      "TX_1779874451286_7911",
      "TX_1779876967475_17784",
      "TX_1779878833403_64961",
      "TX_1779879504975_7366",
      "TX_1779882274796_57121",
      "TX_1779888391269_98290",
      "TX_1779902514828_90298",
      "TX_1779913350410_29191",
      "TX_1779947180970_81337",
      "TX_1779961983125_8885",
      "TX_1780175091911_51759",
      "MNFY|48|20260527100107|071627"
    ],
    "activationRows": [],
    "reason": "not_present"
  },
  {
    "name": "Elijah Aniedi Patrick",
    "email": "elijahpatrick875@gmail.com",
    "refs": [
      "TX_1780003398624_23244",
      "TX_1779987248069_76459",
      "TX_1779987342997_3385",
      "MNFY|22|20260528175410|132688"
    ],
    "activationRows": [],
    "reason": "not_present"
  },
  {
    "name": "Isaiah 7",
    "email": "otina2298@gmail.com",
    "refs": [
      "TX_1779964503615_20904",
      "TX_1779957247628_30854",
      "TX_1779963783670_20911",
      "TX_1779963832103_67845",
      "TX_1779964004274_6896",
      "MNFY|26|20260528112354|119498"
    ],
    "activationRows": [],
    "reason": "not_present"
  },
  {
    "name": "Afeez",
    "email": "oyekanmiafeez259@gmail.com",
    "refs": [
      "TX_1780162542635_17066",
      "TX_1779793731605_92759",
      "TX_1779793789611_59098",
      "TX_1779793838210_92545",
      "MNFY|14|20260526120953|029941",
      "TX_1779794098048_52240",
      "TX_1779990110296_59458",
      "TX_1779990325853_70757",
      "TX_1779991026150_19181",
      "TX_1779991194059_89723",
      "TX_1779991330016_55000",
      "TX_1780047640105_57771",
      "MNFY|88|20260528185708|130223"
    ],
    "activationRows": [],
    "reason": "not_present"
  },
  {
    "name": "Kasarachi Joseph",
    "email": "chijiokebetter@yahoo.com",
    "refs": [
      "TX_1779956985959_76271",
      "TX_1779956713671_43385",
      "MNFY|88|20260528092516|112293"
    ],
    "activationRows": [],
    "reason": "not_present"
  },
  {
    "name": "Samuel nwabueze",
    "email": "samuelwilliams095@gmail.com",
    "refs": [
      "TX_1780041119553_82800",
      "TX_1780000479480_53565",
      "TX_1780000699652_83871",
      "TX_1780040003558_74524",
      "MNFY|14|20260528213441|135671"
    ],
    "activationRows": [],
    "reason": "not_present"
  },
  {
    "name": "Godswill Anyak",
    "email": "angelojessemars@gmail.com",
    "refs": [
      "TX_1780487242561_89021",
      "TX_1780474517575_6212",
      "TX_1780474863893_8158",
      "TX_1780474971298_95012",
      "MNFY|68|20260603091519|023856"
    ],
    "activationRows": [],
    "reason": "not_present"
  },
  {
    "name": "Victor Nwakudu",
    "email": "vickkybrass@gmail.com",
    "refs": [
      "TX_1780114938684_36617",
      "TX_1780114115686_36704",
      "TX_1780114340360_2865",
      "TX_1780114449916_94153",
      "TX_1780114720545_40890",
      "TX_1780114809563_71639",
      "TX_1780114910997_71467",
      "MNFY|35|20260530050838|020909"
    ],
    "activationRows": [],
    "reason": "not_present"
  },
  {
    "name": "Emi",
    "email": "ermiekeyzodosa5960@gmail.com",
    "refs": [
      "TX_1780333298460_61673",
      "TX_1780329689990_79150",
      "TX_1780330084371_84083",
      "TX_1780330284099_4844",
      "TX_1780330755658_53165",
      "MNFY|48|20260601170133|060836"
    ],
    "activationRows": [],
    "reason": "not_present"
  },
  {
    "name": "ikechukwu  Oscar Ogbonna",
    "email": "oscaroike@gmail.com",
    "refs": [
      "TX_1780079517975_34987",
      "TX_1780078769620_43379",
      "TX_1780079022822_92350",
      "MNFY|07|20260529191932|005644"
    ],
    "activationRows": [],
    "reason": "not_present"
  },
  {
    "name": "Igwe Juliet",
    "email": "igwej7403@gmail.com",
    "refs": [
      "TX_1780313438024_62378",
      "TX_1780308363363_74888",
      "TX_1780308507697_52210",
      "TX_1780308664710_63039",
      "MNFY|43|20260601110605|063640"
    ],
    "activationRows": [],
    "reason": "not_present"
  },
  {
    "name": "Christiana Asuquo",
    "email": "tinaenobong@gmail.com",
    "refs": [
      "TX_1780199647628_53158",
      "TX_1780199363960_83210",
      "TX_1780199562095_2863",
      "MNFY|44|20260531044926|011354"
    ],
    "activationRows": [],
    "reason": "not_present"
  },
  {
    "name": "OG billions",
    "email": "ukachukwuchijiokemartins@gmail.com",
    "refs": [
      "TX_1780253482905_39232",
      "TX_1780225018931_83120",
      "TX_1780252674395_91174",
      "MNFY|73|20260531193757|030251"
    ],
    "activationRows": [],
    "reason": "not_present"
  },
  {
    "name": "Chinaeme Anselm Nwabunwanne",
    "email": "chinaemeanselm01@gmail.com",
    "refs": [
      "TX_1780241753680_59928",
      "TX_1779794487099_96266",
      "TX_1779827918483_14705",
      "TX_1779875228714_87619",
      "TX_1779875435207_76075",
      "TX_1780074658925_31126",
      "MNFY|34|20260527104711|071149"
    ],
    "activationRows": [],
    "reason": "not_present"
  },
  {
    "name": "Otukupe Peter Eze",
    "email": "ezepeter199531@gmail.com",
    "refs": [
      "TX_1779981068261_6510",
      "TX_1779891271091_18307",
      "TX_1779891452323_24910",
      "TX_1779891537840_24987",
      "TX_1779891635358_61692",
      "MNFY|34|20260527151438|079685"
    ],
    "activationRows": [],
    "reason": "not_present"
  },
  {
    "name": "Divine Okenna",
    "email": "divineokenna105@gmail.com",
    "refs": [
      "TX_1779794025115_76958",
      "TX_1779793532161_93655",
      "TX_1779793733923_76400",
      "TX_1779793991830_99144",
      "MNFY|14|20260526120536|029819"
    ],
    "activationRows": [],
    "reason": "not_present"
  },
  {
    "name": "Victory chy",
    "email": "victorychyjude@gmail.com",
    "refs": [
      "TX_1780340974931_49130",
      "TX_1780008973693_79221",
      "TX_1780009425077_5557",
      "TX_1780009953297_31272",
      "TX_1780010487590_6633",
      "TX_1780033492745_2411",
      "TX_1780057865237_29424",
      "TX_1780062721867_69496",
      "TX_1780065060648_68427",
      "TX_1780120324710_47169",
      "MNFY|70|20260528235617|141544"
    ],
    "activationRows": [],
    "reason": "not_present"
  }
]